hmd_lib_containers/__init__.py
hmd_lib_containers/hmd_lib_containers.py
hmd_lib_containers/config/__init__.py
hmd_lib_containers/config/build_config.py
hmd_lib_containers-0.1.83.dist-info/METADATA
hmd_lib_containers-0.1.83.dist-info/WHEEL
hmd_lib_containers-0.1.83.dist-info/top_level.txt
hmd_lib_containers-0.1.83.dist-info/RECORD
